mindstorms.py
mindstorms-0.1.2.dist-info/LICENSE
mindstorms-0.1.2.dist-info/WHEEL
mindstorms-0.1.2.dist-info/METADATA
mindstorms-0.1.2.dist-info/RECORD
