Metadata-Version: 2.1
Name: mindstorms
Version: 0.1.2
Summary: Operate LEGO MINDSTORMS Inventor Hub from your computer
Home-page: https://github.com/noamraph/mindstorms
License: MIT
Author: Noam Raphael
Requires-Python: >=3.8,<4.0
Classifier: License :: OSI Approved :: MIT License
Classifier: Programming Language :: Python :: 3
Classifier: Programming Language :: Python :: 3.10
Classifier: Programming Language :: Python :: 3.8
Classifier: Programming Language :: Python :: 3.9
Requires-Dist: rshell (>=0.0.31,<0.0.32)
Project-URL: Repository, https://github.com/noamraph/mindstorms
